urh/__init__.py
urh/colormaps.py
urh/main.py
urh/settings.py
urh/version.py
urh/ainterpretation/AutoInterpretation.py
urh/ainterpretation/Wavelet.py
urh/ainterpretation/__init__.py
urh/awre/AutoAssigner.py
urh/awre/CommonRange.py
urh/awre/FormatFinder.py
urh/awre/Histogram.py
urh/awre/MessageTypeBuilder.py
urh/awre/Preprocessor.py
urh/awre/ProtocolGenerator.py
urh/awre/__init__.py
urh/awre/engines/AddressEngine.py
urh/awre/engines/ChecksumEngine.py
urh/awre/engines/Engine.py
urh/awre/engines/LengthEngine.py
urh/awre/engines/SequenceNumberEngine.py
urh/awre/engines/__init__.py
urh/cli/__init__.py
urh/cli/urh_cli.py
urh/controller/CompareFrameController.py
urh/controller/GeneratorTabController.py
urh/controller/MainController.py
urh/controller/SignalTabController.py
urh/controller/SimulatorTabController.py
urh/controller/__init__.py
urh/controller/dialogs/AdvancedModulationOptionsDialog.py
urh/controller/dialogs/CSVImportDialog.py
urh/controller/dialogs/ContinuousSendDialog.py
urh/controller/dialogs/CostaOptionsDialog.py
urh/controller/dialogs/DecoderDialog.py
urh/controller/dialogs/FilterBandwidthDialog.py
urh/controller/dialogs/FilterDialog.py
urh/controller/dialogs/FuzzingDialog.py
urh/controller/dialogs/MessageTypeDialog.py
urh/controller/dialogs/ModulationParametersDialog.py
urh/controller/dialogs/ModulatorDialog.py
urh/controller/dialogs/OptionsDialog.py
urh/controller/dialogs/ProjectDialog.py
urh/controller/dialogs/ProtocolLabelDialog.py
urh/controller/dialogs/ProtocolSniffDialog.py
urh/controller/dialogs/ReceiveDialog.py
urh/controller/dialogs/SendDialog.py
urh/controller/dialogs/SendRecvDialog.py
urh/controller/dialogs/SignalDetailsDialog.py
urh/controller/dialogs/SimulatorDialog.py
urh/controller/dialogs/SpectrumDialogController.py
urh/controller/dialogs/__init__.py
urh/controller/widgets/ChecksumWidget.py
urh/controller/widgets/DeviceSettingsWidget.py
urh/controller/widgets/ModulationSettingsWidget.py
urh/controller/widgets/PluginFrame.py
urh-2.9.7.dist-info/LICENSE
urh-2.9.7.dist-info/METADATA
urh-2.9.7.dist-info/WHEEL
urh-2.9.7.dist-info/entry_points.txt
urh-2.9.7.dist-info/top_level.txt
urh-2.9.7.dist-info/RECORD
