Metadata-Version: 2.1
Name: urh
Version: 2.9.7
Summary: Universal Radio Hacker: investigate wireless protocols like a boss
Home-page: https://github.com/jopohl/urh
Download-URL: https://github.com/jopohl/urh/tarball/v2.9.7
Author: Johannes Pohl
Author-email: Johannes.Pohl90@gmail.com
License: GNU General Public License (GPL)
License-File: LICENSE
Requires-Dist: numpy
Requires-Dist: psutil
Requires-Dist: cython
Requires-Dist: pyqt5
